vollseg_napari/__init__.py
vollseg_napari/_dock_widget.py
vollseg_napari/_sample_data.py
vollseg_napari/_test_dock_widget.py
vollseg_napari/_version.py
vollseg_napari/napari.yaml
vollseg_napari/_tests/2.8
vollseg_napari/_tests/=0.4.0
vollseg_napari/_tests/__init__.py
vollseg_napari/_tests/plugintest.py
vollseg_napari/_tests/test_open_sample_data.py
vollseg_napari/_tests/test_open_sample_models.py
vollseg_napari/resources/kapoorlogo.png
vollseg_napari-2.4.9.dist-info/METADATA
vollseg_napari-2.4.9.dist-info/WHEEL
vollseg_napari-2.4.9.dist-info/entry_points.txt
vollseg_napari-2.4.9.dist-info/top_level.txt
vollseg_napari-2.4.9.dist-info/RECORD
