Metadata-Version: 2.4
Name: vollseg-napari
Version: 2.4.9
Summary: Irregular cell shape segmentation using VollSeg
Home-page: https://github.com/kapoorlab/vollseg-napari
Author: Varun Kapoor
Author-email: varun.kapoor@kapoorlabs.org
License: BSD 3-Clause License
Project-URL: Source Code, https://github.com/kapoorlab/vollseg-napari
Project-URL: Documentation, https://github.com/kapoorlab/vollseg-napari
Project-URL: Bug Tracker, https://github.com/kapoorlab/vollseg-napari/issues
Project-URL: User Support, https://forum.image.sc/tag/vollseg-napari
Project-URL: Twitter, https://twitter.com/entracod
Classifier: Development Status :: 4 - Beta
Classifier: Intended Audience :: Science/Research
Classifier: Topic :: Scientific/Engineering
Classifier: License :: OSI Approved :: BSD License
Classifier: Operating System :: OS Independent
Classifier: Programming Language :: Python :: 3.7
Classifier: Programming Language :: Python :: 3.8
Classifier: Programming Language :: Python :: 3.9
Classifier: Framework :: napari
Requires-Python: >=3.7
Requires-Dist: vollseg
Requires-Dist: tensorflow; platform_system != "Darwin" or platform_machine != "arm64"
Requires-Dist: tensorflow-macos; platform_system == "Darwin" and platform_machine == "arm64"
Requires-Dist: napari>=0.4.13
Requires-Dist: magicgui>=0.4.0
Requires-Dist: pyqt6
Requires-Dist: pynvml
Provides-Extra: test
Requires-Dist: pytest; extra == "test"
Requires-Dist: pytest-qt; extra == "test"
Requires-Dist: napari[pyqt]>=0.4.13; extra == "test"
Dynamic: author
Dynamic: author-email
Dynamic: classifier
Dynamic: description
Dynamic: description-content-type
Dynamic: home-page
Dynamic: license
Dynamic: project-url
Dynamic: provides-extra
Dynamic: requires-dist
Dynamic: requires-python
Dynamic: summary
